markup_adaptation/Adaptations.xsd
markup_adaptation/__init__.py
markup_adaptation/actions.py
markup_adaptation/adaptation.py
markup_adaptation/adaptation_schema.xml
markup_adaptation/common.py
markup_adaptation/configuration.py
markup_adaptation/controls.py
markup_adaptation/domain.py
markup_adaptation/errors.py
markup_adaptation/expressions.py
markup_adaptation/parser.py
markup_adaptation/paths.py
markup_adaptation/svg_template.py
markup_adaptation/xml_domain.py
markup_adaptation/formatting/__init__.py
markup_adaptation/formatting/functional.py
markup_adaptation/formatting/regen.py
markup_adaptation/formatting/tokenizer.py
markup_adaptation/formatting/tests/__init__.py
markup_adaptation/formatting/tests/test_functionals.py
markup_adaptation/formatting/tests/test_tokenizer.py
markup_adaptation/tests/__init__.py
markup_adaptation/tests/test_common.py
markup_adaptation-1.0.0.dist-info/AUTHORS.txt
markup_adaptation-1.0.0.dist-info/LICENSE.txt
markup_adaptation-1.0.0.dist-info/METADATA
markup_adaptation-1.0.0.dist-info/WHEEL
markup_adaptation-1.0.0.dist-info/top_level.txt
markup_adaptation-1.0.0.dist-info/zip-safe
markup_adaptation-1.0.0.dist-info/RECORD
