Metadata-Version: 2.1
Name: markup-adaptation
Version: 1.0.0
Summary: A library for managing markup-based templates.
Home-page: https://github.com/high-dimensional/markup-adaptation
Author: High Dimensional Neurology Group, UCL
Author-email: pypi@highdimensional.net
License: BSD-3-Clause
Platform: any
Classifier: Framework :: Django
Classifier: Framework :: Wagtail
Classifier: Programming Language :: Python :: 3
Classifier: Programming Language :: Python :: 3.8
Classifier: License :: OSI Approved :: BSD License
Classifier: Operating System :: OS Independent
Requires-Python: >=3.8
License-File: LICENSE.txt
License-File: AUTHORS.txt
